pyforged/__bases__.py
pyforged/__errors__.py
pyforged/__futures__.py
pyforged/__init__.py
pyforged/__models__.py
pyforged/__olds__.py
pyforged/blacksmith.py
pyforged/build.py
pyforged/metaspaces.py
pyforged/namespaces.py
pyforged/services.py
pyforged/commons/__init__.py
pyforged/commons/definitions/__init__.py
pyforged/commons/patterns/__init__.py
pyforged/commons/patterns/execution.py
pyforged/commons/patterns/mixins.py
pyforged/commons/patterns/state.py
pyforged/commons/patterns/undefined.py
pyforged/ecosystem/__init__.py
pyforged/ecosystem/bases.py
pyforged/ecosystem/forest.py
pyforged/engine/__init__.py
pyforged/engine/deployment.py
pyforged/engine/environments.py
pyforged/engine/ignition.py
pyforged/engine/parts.py
pyforged/engine/systems.py
pyforged/utilities/__init__.py
pyforged/utilities/assorted.py
pyforged/utilities/files.py
pyforged/utilities/locking.py
pyforged/utilities/misc.py
pyforged/utilities/secrets.py
pyforged/utilities/structures.py
pyforged/utilities/text.py
pyforged/utilities/tasking/__init__.py
pyforged/utilities/tasking/queues.py
pyforged/utilities/tasking/runner.py
pyforged/utilities/tasking/tasks.py
pyforged-0.2.6.dist-info/licenses/LICENSE.md
pyforged-0.2.6.dist-info/METADATA
pyforged-0.2.6.dist-info/WHEEL
pyforged-0.2.6.dist-info/top_level.txt
pyforged-0.2.6.dist-info/RECORD
