Metadata-Version: 2.4
Name: pyforged
Version: 0.2.6
Summary: The PyForged EcoSystem (core).
Author-email: DirtyWork Solutions Limited <pyforge-core@open.dirtywork.solutions>
License: # MIT License
Project-URL: Homepage, https://open.dirtywork.solutions/pyforged
Project-URL: Documentation, https://github.com/DirtyWork-Solutions/RuneCaller/docs/INDEX.md
Project-URL: Source, https://github.com/DirtyWork-Solutions/RuneCaller
Project-URL: Issues, https://github.com/DirtyWork-Solutions/RuneCaller/tree/main/.github/ISSUE_TEMPLATE
Classifier: Programming Language :: Python :: 3
Classifier: Programming Language :: Python :: 3.13
Classifier: Programming Language :: Python :: Implementation :: CPython
Classifier: License :: OSI Approved :: MIT License
Classifier: Operating System :: OS Independent
Classifier: Development Status :: 2 - Pre-Alpha
Classifier: Environment :: Console
Classifier: Intended Audience :: Developers
Classifier: Topic :: System
Classifier: Topic :: Software Development :: Libraries :: Python Modules
Classifier: Topic :: Utilities
Classifier: Topic :: System :: Installation/Setup
Requires-Python: >=3.13
License-File: LICENSE.md
Requires-Dist: antlr4-python3-runtime~=4.9.3
Requires-Dist: pytest~=8.3.5
Requires-Dist: pytest-metadata~=3.1.1
Requires-Dist: pydantic~=2.10.6
Requires-Dist: cryptography~=44.0.2
Requires-Dist: requests~=2.32.3
Requires-Dist: pyyaml~=6.0.2
Requires-Dist: cachetools~=5.5.2
Provides-Extra: suite
Requires-Dist: bedrocked~=0.1.4; extra == "suite"
Requires-Dist: runecaller~=0.1.4; extra == "suite"
Requires-Dist: wardkeeper~=0.1.0; extra == "suite"
Provides-Extra: std
Requires-Dist: bedrocked~=0.1.4; extra == "std"
Requires-Dist: runecaller~=0.1.4; extra == "std"
Requires-Dist: wardkeeper~=0.1.0; extra == "std"
Provides-Extra: dev
Dynamic: license-file
